sqlite_kv/__init__.py
sqlite_kv/api/__init__.py
sqlite_kv/api/api.py
sqlite_kv/decorators/__init__.py
sqlite_kv/decorators/decorators.py
sqlite_kv/ops/__init__.py
sqlite_kv/ops/ops.py
sqlite_kv-0.1.2.dist-info/METADATA
sqlite_kv-0.1.2.dist-info/WHEEL
sqlite_kv-0.1.2.dist-info/top_level.txt
sqlite_kv-0.1.2.dist-info/RECORD
